examples/main_analyze_results.py
examples/main_cleanup.py
examples/main_run_experiments.py
examples/main_utils_demo.py
examples/my_experiment.py
ztxexp/__init__.py
ztxexp/analyzer.py
ztxexp/environment.py
ztxexp/manager.py
ztxexp/runner.py
ztxexp/utils.py
ztxexp-0.1.0.dist-info/licenses/LICENSE
ztxexp-0.1.0.dist-info/METADATA
ztxexp-0.1.0.dist-info/WHEEL
ztxexp-0.1.0.dist-info/top_level.txt
ztxexp-0.1.0.dist-info/RECORD
