Metadata-Version: 2.4
Name: ztxexp
Version: 0.1.0
Summary: 一个轻量、强大的Python库，旨在简化计算实验的管理、执行和分析。
Author-email: ztxtech <ztxtech@foxmail.com>
License: MIT License
Project-URL: Homepage, https://ztxtech.github.io/ztxexp/
Project-URL: Repository, https://github.com/ztxtech/ztxexp
Keywords: experiment management,machine learning,deep learning,reproducibility,parameter search,data science,pytorch
Classifier: Development Status :: 4 - Beta
Classifier: Programming Language :: Python :: 3
Classifier: Programming Language :: Python :: 3.8
Classifier: Programming Language :: Python :: 3.9
Classifier: Programming Language :: Python :: 3.10
Classifier: Programming Language :: Python :: 3.11
Classifier: License :: OSI Approved :: MIT License
Classifier: Operating System :: OS Independent
Classifier: Intended Audience :: Developers
Classifier: Intended Audience :: Science/Research
Classifier: Topic :: Scientific/Engineering
Classifier: Topic :: Software Development :: Libraries :: Python Modules
Classifier: Topic :: Utilities
Requires-Python: >=3.8
License-File: LICENSE
Requires-Dist: torch
Requires-Dist: numpy
Requires-Dist: psutil
Requires-Dist: dill
Requires-Dist: joblib
Requires-Dist: pandas
Dynamic: license-file
